[{"_allAttributes":null,"_properties":null,"_methods":null,"file":"/Users/coastalcloud/repo/sf-self-registration/force-app/main/default/lwc/registerCommunityUser/registerCommunityUser.js","metadata":{"decorators":[{"type":"api","targets":[{"type":"property","name":"title","value":{"type":"unresolved"}},{"type":"property","name":"usernamePostFix","value":{"type":"unresolved"}},{"type":"property","name":"startURL","value":{"type":"unresolved"}},{"type":"property","name":"includePasswordField","value":{"type":"unresolved"}}]}],"declarationLoc":{"start":{"line":11,"column":0},"end":{"line":140,"column":1}},"classMembers":[{"type":"property","name":"title","loc":{"start":{"line":13,"column":4},"end":{"line":13,"column":14}},"decorator":"api","value":{"type":"unresolved"}},{"type":"property","name":"usernamePostFix","loc":{"start":{"line":14,"column":4},"end":{"line":14,"column":24}},"decorator":"api","value":{"type":"unresolved"}},{"type":"property","name":"startURL","loc":{"start":{"line":15,"column":4},"end":{"line":15,"column":17}},"decorator":"api","value":{"type":"unresolved"}},{"type":"property","name":"includePasswordField","loc":{"start":{"line":16,"column":4},"end":{"line":16,"column":29}},"decorator":"api","value":{"type":"unresolved"}},{"type":"property","name":"accountName","loc":{"start":{"line":18,"column":4},"end":{"line":18,"column":20}}},{"type":"property","name":"firstName","loc":{"start":{"line":19,"column":4},"end":{"line":19,"column":18}}},{"type":"property","name":"lastName","loc":{"start":{"line":20,"column":4},"end":{"line":20,"column":17}}},{"type":"property","name":"email","loc":{"start":{"line":21,"column":4},"end":{"line":21,"column":14}}},{"type":"property","name":"password","loc":{"start":{"line":23,"column":4},"end":{"line":23,"column":17}}},{"type":"property","name":"confirmPassword","loc":{"start":{"line":24,"column":4},"end":{"line":24,"column":24}}},{"type":"property","name":"error","loc":{"start":{"line":26,"column":4},"end":{"line":26,"column":17}}},{"type":"property","name":"isLoading","loc":{"start":{"line":27,"column":4},"end":{"line":27,"column":21}}},{"type":"property","name":"username","loc":{"start":{"line":29,"column":4},"end":{"line":31,"column":5}}},{"type":"method","name":"onkeyup","loc":{"start":{"line":32,"column":4},"end":{"line":37,"column":5}}},{"type":"method","name":"setValues","loc":{"start":{"line":39,"column":4},"end":{"line":46,"column":5}}},{"type":"method","name":"register","loc":{"start":{"line":48,"column":4},"end":{"line":78,"column":5}}},{"type":"method","name":"getConfig","loc":{"start":{"line":81,"column":4},"end":{"line":96,"column":5}}},{"type":"method","name":"validateEmail","loc":{"start":{"line":99,"column":4},"end":{"line":116,"column":5}}},{"type":"method","name":"validateUsername","loc":{"start":{"line":118,"column":4},"end":{"line":135,"column":5}}},{"type":"method","name":"loading","loc":{"start":{"line":137,"column":4},"end":{"line":139,"column":5}}}],"exports":[{"type":"ExportDefaultDeclaration"}]},"updatedAt":"2023-06-08T15:27:37.585Z"}]